install_qt_creator/desktop.py
install_qt_creator/main.py
install_qt_creator-2025.2.3.1.dist-info/METADATA
install_qt_creator-2025.2.3.1.dist-info/WHEEL
install_qt_creator-2025.2.3.1.dist-info/entry_points.txt
install_qt_creator-2025.2.3.1.dist-info/licenses/LICENSE
install_qt_creator-2025.2.3.1.dist-info/RECORD
