Metadata-Version: 2.4
Name: install-qt-creator
Version: 2025.2.3.1
Summary: install qt creator using MSYS2
Project-URL: Repository, https://github.com/soda92/install-qt-creator
License-File: LICENSE
Requires-Python: >=3.10
Requires-Dist: pywin32>=308
